README.md
setup.py
discord_ext_disutils.egg-info/PKG-INFO
discord_ext_disutils.egg-info/SOURCES.txt
discord_ext_disutils.egg-info/dependency_links.txt
discord_ext_disutils.egg-info/requires.txt
discord_ext_disutils.egg-info/top_level.txt
disutils/__init__.py
disutils/_version.py
disutils/errors.py
disutils/topgg.py