Metadata-Version: 2.1
Name: discord-ext-disutils
Version: 1.0.1
Summary: Disutils is a very useful library made to be used with discord.py
Author: Pranoy Majumdar
Classifier: Programming Language :: Python :: 3
Classifier: License :: OSI Approved :: MIT License
Classifier: Operating System :: OS Independent
Requires-Python: >= 3.7
